{
  "species_constant": "SPECIES_LAIRON",
  "family_constant": "P_FAMILY_ARON",
  "entries": [
    {
      "type": "field",
      "name": "baseHP",
      "value": "60"
    },
    {
      "type": "field",
      "name": "baseAttack",
      "value": "90"
    },
    {
      "type": "field",
      "name": "baseDefense",
      "value": "140"
    },
    {
      "type": "field",
      "name": "baseSpeed",
      "value": "40"
    },
    {
      "type": "field",
      "name": "baseSpAttack",
      "value": "50"
    },
    {
      "type": "field",
      "name": "baseSpDefense",
      "value": "50"
    },
    {
      "type": "field",
      "name": "types",
      "value": "MON_TYPES(TYPE_STEEL, TYPE_ROCK)"
    },
    {
      "type": "field",
      "name": "catchRate",
      "value": "90"
    },
    {
      "type": "field",
      "name": "expYield",
      "value": "(P_UPDATED_EXP_YIELDS >= GEN_5) ? 151 : 152"
    },
    {
      "type": "field",
      "name": "evYield_Defense",
      "value": "2"
    },
    {
      "type": "field",
      "name": "itemRare",
      "value": "ITEM_HARD_STONE"
    },
    {
      "type": "field",
      "name": "genderRatio",
      "value": "PERCENT_FEMALE(50)"
    },
    {
      "type": "field",
      "name": "eggCycles",
      "value": "35"
    },
    {
      "type": "field",
      "name": "friendship",
      "value": "35"
    },
    {
      "type": "field",
      "name": "growthRate",
      "value": "GROWTH_SLOW"
    },
    {
      "type": "field",
      "name": "eggGroups",
      "value": "MON_EGG_GROUPS(EGG_GROUP_MONSTER)"
    },
    {
      "type": "field",
      "name": "abilities",
      "value": "{ ABILITY_STURDY, ABILITY_ROCK_HEAD, ABILITY_HEAVY_METAL }"
    },
    {
      "type": "field",
      "name": "bodyColor",
      "value": "BODY_COLOR_GRAY"
    },
    {
      "type": "field",
      "name": "speciesName",
      "value": "_(\"Lairon\")"
    },
    {
      "type": "field",
      "name": "cryId",
      "value": "CRY_LAIRON"
    },
    {
      "type": "field",
      "name": "natDexNum",
      "value": "NATIONAL_DEX_LAIRON"
    },
    {
      "type": "field",
      "name": "categoryName",
      "value": "_(\"Iron Armor\")"
    },
    {
      "type": "field",
      "name": "height",
      "value": "9"
    },
    {
      "type": "field",
      "name": "weight",
      "value": "1200"
    },
    {
      "type": "field",
      "name": "description",
      "value": "COMPOUND_STRING(\n\"When two Lairon meet in the wild, they\\n\"\n\"fight for territory by bashing into each\\n\"\n\"other with their steel bodies. The sound\\n\"\n\"of their collision carries for miles.\")"
    },
    {
      "type": "field",
      "name": "pokemonScale",
      "value": "275"
    },
    {
      "type": "field",
      "name": "pokemonOffset",
      "value": "12"
    },
    {
      "type": "field",
      "name": "trainerScale",
      "value": "256"
    },
    {
      "type": "field",
      "name": "trainerOffset",
      "value": "0"
    },
    {
      "type": "field",
      "name": "frontPic",
      "value": "gMonFrontPic_Lairon"
    },
    {
      "type": "field",
      "name": "frontPicSize",
      "value": "P_GBA_STYLE_SPECIES_GFX ? MON_COORDS_SIZE(56, 40) : MON_COORDS_SIZE(56, 48)"
    },
    {
      "type": "field",
      "name": "frontPicYOffset",
      "value": "P_GBA_STYLE_SPECIES_GFX ? 13 : 8"
    },
    {
      "type": "field",
      "name": "frontAnimFrames",
      "value": "ANIM_FRAMES(\nANIMCMD_FRAME(0, 12),\nANIMCMD_FRAME(1, 29),\nANIMCMD_FRAME(0, 10),\nANIMCMD_FRAME(1, 29),\nANIMCMD_FRAME(0, 1),\n)"
    },
    {
      "type": "field",
      "name": "frontAnimId",
      "value": "ANIM_V_SQUISH_AND_BOUNCE"
    },
    {
      "type": "field",
      "name": "backPic",
      "value": "gMonBackPic_Lairon"
    },
    {
      "type": "field",
      "name": "backPicSize",
      "value": "P_GBA_STYLE_SPECIES_GFX ? MON_COORDS_SIZE(64, 32) : MON_COORDS_SIZE(64, 40)"
    },
    {
      "type": "field",
      "name": "backPicYOffset",
      "value": "P_GBA_STYLE_SPECIES_GFX ? 17 : 15"
    },
    {
      "type": "field",
      "name": "backAnimId",
      "value": "BACK_ANIM_V_SHAKE"
    },
    {
      "type": "field",
      "name": "palette",
      "value": "gMonPalette_Lairon"
    },
    {
      "type": "field",
      "name": "shinyPalette",
      "value": "gMonShinyPalette_Lairon"
    },
    {
      "type": "field",
      "name": "iconSprite",
      "value": "gMonIcon_Lairon"
    },
    {
      "type": "field",
      "name": "iconPalIndex",
      "value": "2"
    },
    {
      "type": "field",
      "name": "pokemonJumpType",
      "value": "PKMN_JUMP_TYPE_NONE"
    },
    {
      "type": "macro",
      "name": "SHADOW",
      "args": "4, 2, SHADOW_SIZE_L",
      "has_comma": false
    },
    {
      "type": "macro",
      "name": "FOOTPRINT",
      "args": "Lairon",
      "has_comma": false
    },
    {
      "type": "macro",
      "name": "OVERWORLD",
      "args": "sPicTable_Lairon,\nSIZE_32x32,\nSHADOW_SIZE_M,\nTRACKS_FOOT,\nsAnimTable_Following,\ngOverworldPalette_Lairon,\ngShinyOverworldPalette_Lairon",
      "has_comma": false
    },
    {
      "type": "field",
      "name": "levelUpLearnset",
      "value": "sLaironLevelUpLearnset"
    },
    {
      "type": "field",
      "name": "teachableLearnset",
      "value": "sLaironTeachableLearnset"
    },
    {
      "type": "field",
      "name": "evolutions",
      "value": "EVOLUTION({EVO_LEVEL, 42, SPECIES_AGGRON})"
    }
  ]
}